{"Timestamp":120973.979439,"Documents":1,"Frames":1,"JSEventListeners":245,"Nodes":2465,"LayoutCount":67,"RecalcStyleCount":104,"LayoutDuration":0.051123,"RecalcStyleDuration":0.02737,"ScriptDuration":0.226225,"TaskDuration":6.186821,"JSHeapUsedSize":399296300,"JSHeapTotalSize":425369600}
{"Timestamp":120980.758424,"Documents":1,"Frames":1,"JSEventListeners":245,"Nodes":2465,"LayoutCount":67,"RecalcStyleCount":104,"LayoutDuration":0.053931,"RecalcStyleDuration":0.026754,"ScriptDuration":0.22336,"TaskDuration":6.156901,"JSHeapUsedSize":347647256,"JSHeapTotalSize":371019776}
{"Timestamp":120987.633168,"Documents":1,"Frames":1,"JSEventListeners":245,"Nodes":2465,"LayoutCount":67,"RecalcStyleCount":105,"LayoutDuration":0.049883,"RecalcStyleDuration":0.027188,"ScriptDuration":0.231109,"TaskDuration":6.265833,"JSHeapUsedSize":395819936,"JSHeapTotalSize":427057152}
{"Timestamp":120994.406061,"Documents":1,"Frames":1,"JSEventListeners":245,"Nodes":2465,"LayoutCount":67,"RecalcStyleCount":104,"LayoutDuration":0.050532,"RecalcStyleDuration":0.027648,"ScriptDuration":0.226908,"TaskDuration":6.15558,"JSHeapUsedSize":395906180,"JSHeapTotalSize":427745280}
{"Timestamp":121001.234097,"Documents":1,"Frames":1,"JSEventListeners":245,"Nodes":2465,"LayoutCount":67,"RecalcStyleCount":105,"LayoutDuration":0.053463,"RecalcStyleDuration":0.027853,"ScriptDuration":0.234437,"TaskDuration":6.236955,"JSHeapUsedSize":356161000,"JSHeapTotalSize":387063808}
{"Timestamp":121008.488813,"Documents":1,"Frames":1,"JSEventListeners":245,"Nodes":2465,"LayoutCount":67,"RecalcStyleCount":105,"LayoutDuration":0.050395,"RecalcStyleDuration":0.029277,"ScriptDuration":0.239422,"TaskDuration":6.618938,"JSHeapUsedSize":342565512,"JSHeapTotalSize":372068352}
{"Timestamp":121015.844689,"Documents":1,"Frames":1,"JSEventListeners":245,"Nodes":2465,"LayoutCount":67,"RecalcStyleCount":104,"LayoutDuration":0.052121,"RecalcStyleDuration":0.028156,"ScriptDuration":0.236108,"TaskDuration":6.761376,"JSHeapUsedSize":395834408,"JSHeapTotalSize":427745280}
{"Timestamp":121023.257859,"Documents":1,"Frames":1,"JSEventListeners":245,"Nodes":2465,"LayoutCount":67,"RecalcStyleCount":104,"LayoutDuration":0.051457,"RecalcStyleDuration":0.028217,"ScriptDuration":0.229861,"TaskDuration":6.788063,"JSHeapUsedSize":354329616,"JSHeapTotalSize":384180224}
{"Timestamp":121030.259687,"Documents":1,"Frames":1,"JSEventListeners":245,"Nodes":2465,"LayoutCount":67,"RecalcStyleCount":104,"LayoutDuration":0.051614,"RecalcStyleDuration":0.028004,"ScriptDuration":0.22714,"TaskDuration":6.388519,"JSHeapUsedSize":396201656,"JSHeapTotalSize":427483136}
{"Timestamp":121037.465124,"Documents":1,"Frames":1,"JSEventListeners":245,"Nodes":2465,"LayoutCount":67,"RecalcStyleCount":104,"LayoutDuration":0.051467,"RecalcStyleDuration":0.027562,"ScriptDuration":0.229151,"TaskDuration":6.602197,"JSHeapUsedSize":400648460,"JSHeapTotalSize":426172416}
