{"Timestamp":75326.816308,"Documents":1,"Frames":1,"JSEventListeners":553,"Nodes":7699,"LayoutCount":215,"RecalcStyleCount":343,"LayoutDuration":0.071538,"RecalcStyleDuration":0.043294,"ScriptDuration":0.347336,"TaskDuration":5.555726,"JSHeapUsedSize":180998188,"JSHeapTotalSize":199278592}
{"Timestamp":75333.750114,"Documents":1,"Frames":1,"JSEventListeners":527,"Nodes":7792,"LayoutCount":202,"RecalcStyleCount":308,"LayoutDuration":0.077778,"RecalcStyleDuration":0.048828,"ScriptDuration":0.427123,"TaskDuration":5.68144,"JSHeapUsedSize":180554556,"JSHeapTotalSize":199016448}
{"Timestamp":75340.298803,"Documents":1,"Frames":1,"JSEventListeners":539,"Nodes":7678,"LayoutCount":198,"RecalcStyleCount":313,"LayoutDuration":0.070283,"RecalcStyleDuration":0.041237,"ScriptDuration":0.348147,"TaskDuration":5.735449,"JSHeapUsedSize":177206848,"JSHeapTotalSize":198230016}
{"Timestamp":75346.761634,"Documents":1,"Frames":1,"JSEventListeners":525,"Nodes":7657,"LayoutCount":182,"RecalcStyleCount":284,"LayoutDuration":0.069168,"RecalcStyleDuration":0.041002,"ScriptDuration":0.347321,"TaskDuration":5.822717,"JSHeapUsedSize":177011028,"JSHeapTotalSize":195084288}
{"Timestamp":75354.177115,"Documents":1,"Frames":1,"JSEventListeners":592,"Nodes":7744,"LayoutCount":251,"RecalcStyleCount":406,"LayoutDuration":0.07432,"RecalcStyleDuration":0.045727,"ScriptDuration":0.372165,"TaskDuration":6.137672,"JSHeapUsedSize":187272720,"JSHeapTotalSize":206356480}
{"Timestamp":75360.644464,"Documents":1,"Frames":1,"JSEventListeners":553,"Nodes":7828,"LayoutCount":232,"RecalcStyleCount":361,"LayoutDuration":0.076609,"RecalcStyleDuration":0.04772,"ScriptDuration":0.405096,"TaskDuration":5.65872,"JSHeapUsedSize":181416732,"JSHeapTotalSize":201375744}
{"Timestamp":75367.15558,"Documents":1,"Frames":1,"JSEventListeners":592,"Nodes":7744,"LayoutCount":250,"RecalcStyleCount":405,"LayoutDuration":0.077799,"RecalcStyleDuration":0.04453,"ScriptDuration":0.358232,"TaskDuration":5.708627,"JSHeapUsedSize":187361464,"JSHeapTotalSize":205045760}
{"Timestamp":75373.680991,"Documents":1,"Frames":1,"JSEventListeners":545,"Nodes":7687,"LayoutCount":206,"RecalcStyleCount":326,"LayoutDuration":0.075666,"RecalcStyleDuration":0.042539,"ScriptDuration":0.327545,"TaskDuration":5.673742,"JSHeapUsedSize":179132288,"JSHeapTotalSize":199016448}
{"Timestamp":75379.946882,"Documents":1,"Frames":1,"JSEventListeners":545,"Nodes":7687,"LayoutCount":206,"RecalcStyleCount":326,"LayoutDuration":0.069857,"RecalcStyleDuration":0.041861,"ScriptDuration":0.328201,"TaskDuration":5.557628,"JSHeapUsedSize":177555460,"JSHeapTotalSize":199540736}
{"Timestamp":75386.353529,"Documents":1,"Frames":1,"JSEventListeners":529,"Nodes":7663,"LayoutCount":186,"RecalcStyleCount":292,"LayoutDuration":0.06577,"RecalcStyleDuration":0.04261,"ScriptDuration":0.34562,"TaskDuration":5.700917,"JSHeapUsedSize":174247456,"JSHeapTotalSize":196919296}
