{"Timestamp":77991.640843,"Documents":1,"Frames":1,"JSEventListeners":521,"Nodes":7753,"LayoutCount":187,"RecalcStyleCount":292,"LayoutDuration":0.071112,"RecalcStyleDuration":0.04884,"ScriptDuration":0.418453,"TaskDuration":10.967271,"JSHeapUsedSize":306251924,"JSHeapTotalSize":334745600}
{"Timestamp":78004.503914,"Documents":1,"Frames":1,"JSEventListeners":553,"Nodes":7748,"LayoutCount":226,"RecalcStyleCount":358,"LayoutDuration":0.07978,"RecalcStyleDuration":0.051896,"ScriptDuration":0.420567,"TaskDuration":11.140687,"JSHeapUsedSize":318050904,"JSHeapTotalSize":350892032}
{"Timestamp":78016.38573,"Documents":1,"Frames":1,"JSEventListeners":553,"Nodes":7748,"LayoutCount":225,"RecalcStyleCount":357,"LayoutDuration":0.078651,"RecalcStyleDuration":0.052872,"ScriptDuration":0.434002,"TaskDuration":10.832585,"JSHeapUsedSize":318656948,"JSHeapTotalSize":350629888}
{"Timestamp":78028.112166,"Documents":1,"Frames":1,"JSEventListeners":521,"Nodes":7753,"LayoutCount":187,"RecalcStyleCount":293,"LayoutDuration":0.071731,"RecalcStyleDuration":0.047872,"ScriptDuration":0.405597,"TaskDuration":10.643293,"JSHeapUsedSize":305365972,"JSHeapTotalSize":336842752}
{"Timestamp":78040.645966,"Documents":1,"Frames":1,"JSEventListeners":507,"Nodes":7725,"LayoutCount":179,"RecalcStyleCount":271,"LayoutDuration":0.073157,"RecalcStyleDuration":0.048912,"ScriptDuration":0.482473,"TaskDuration":11.107987,"JSHeapUsedSize":289141400,"JSHeapTotalSize":343502848}
{"Timestamp":78052.360231,"Documents":1,"Frames":1,"JSEventListeners":521,"Nodes":7815,"LayoutCount":192,"RecalcStyleCount":298,"LayoutDuration":0.072137,"RecalcStyleDuration":0.047217,"ScriptDuration":0.459088,"TaskDuration":10.35445,"JSHeapUsedSize":306434888,"JSHeapTotalSize":341299200}
{"Timestamp":78065.470932,"Documents":1,"Frames":1,"JSEventListeners":553,"Nodes":7748,"LayoutCount":225,"RecalcStyleCount":357,"LayoutDuration":0.080291,"RecalcStyleDuration":0.050875,"ScriptDuration":0.41991,"TaskDuration":11.283035,"JSHeapUsedSize":315085208,"JSHeapTotalSize":349319168}
{"Timestamp":78077.617269,"Documents":1,"Frames":1,"JSEventListeners":521,"Nodes":7786,"LayoutCount":192,"RecalcStyleCount":298,"LayoutDuration":0.073499,"RecalcStyleDuration":0.049234,"ScriptDuration":0.520317,"TaskDuration":10.967019,"JSHeapUsedSize":300012356,"JSHeapTotalSize":336056320}
{"Timestamp":78089.256541,"Documents":1,"Frames":1,"JSEventListeners":507,"Nodes":7731,"LayoutCount":176,"RecalcStyleCount":263,"LayoutDuration":0.076932,"RecalcStyleDuration":0.047527,"ScriptDuration":0.412704,"TaskDuration":9.479249,"JSHeapUsedSize":297012888,"JSHeapTotalSize":324263936}
{"Timestamp":78102.00488,"Documents":1,"Frames":1,"JSEventListeners":551,"Nodes":7743,"LayoutCount":223,"RecalcStyleCount":353,"LayoutDuration":0.077816,"RecalcStyleDuration":0.051508,"ScriptDuration":0.412806,"TaskDuration":10.969957,"JSHeapUsedSize":314288184,"JSHeapTotalSize":348794880}
